<?xml version="1.0" encoding="UTF-8"?>
<objects serializationModel="Studio.02.00.00">
	<object class="ParameterPreset" id="{5ea58423-ebf6-40e4-9361-9152d9beabb5}">
		<property name="name">
			<value>speed</value>
		</property>
		<relationship name="folder">
			<destination>{4d085830-e400-4b18-abae-20d0b3ed6e47}</destination>
		</relationship>
		<relationship name="parameter">
			<destination>{5913758d-3b19-4569-bced-8f25cce80a3c}</destination>
		</relationship>
	</object>
	<object class="GameParameter" id="{5913758d-3b19-4569-bced-8f25cce80a3c}">
		<property name="maximum">
			<value>16</value>
		</property>
		<property name="initialValue">
			<value>0</value>
		</property>
	</object>
</objects>
